<?xml version="1.0" encoding="utf-8" ?>

<odoo>
    <data>
        <record id="l10n_es_mis_report.mis_report_style_l10n_es_l1" model="mis.report.style">
            <field name="suffix_inherit" eval="0" />
            <field name="suffix">€</field>
            <field name="background_color">#AED6F1</field>
        </record>
        <record id="l10n_es_mis_report.mis_report_style_l10n_es_l1i" model="mis.report.style">
            <field name="suffix_inherit" eval="0" />
            <field name="suffix">%</field>
            <field name="background_color">#AED6F1</field>
        </record>
        <record id="l10n_es_mis_report.mis_report_style_l10n_es_l2" model="mis.report.style">
            <field name="suffix_inherit" eval="0" />
            <field name="suffix">€</field>
        </record>
        <record id="l10n_es_mis_report.mis_report_style_l10n_es_l2i" model="mis.report.style">
            <field name="suffix_inherit" eval="0" />
            <field name="suffix">%</field>
        </record>
        <record id="l10n_es_mis_report.mis_report_style_l10n_es_l4i" model="mis.report.style">
            <field name="suffix_inherit" eval="0" />
            <field name="suffix">€</field>
        </record>
    </data>
</odoo>