<?xml version="1.0" encoding="utf-8"?>
<odoo>

    <record id="view_picking_form_operations_tree" model="ir.ui.view">
        <field name="name">stock.picking.form.inherit</field>
        <field name="model">stock.picking</field>
        <field name="inherit_id" ref="stock_picking_invoicing.view_picking_form"/>
        <field name="arch" type="xml">
            <xpath expr="//button[@name='set_to_be_invoiced']" position="attributes">
                <attribute name="invisible" >True</attribute>
            </xpath>
            <xpath expr="//field[@name='is_locked']" position="before">
                <field name="sale_id" invisible="1"/>
                <field name="purchase_id" invisible="1"/>
            </xpath>
            <xpath expr="//field[@name='move_ids_without_package']/tree/field[@name='name']" position="replace">
                
            </xpath>
            <xpath expr="//field[@name='move_ids_without_package']/tree/field[@name='invoice_state']" position="attributes">
                <attribute name="invisible" >True</attribute>
            </xpath>
            <xpath expr="//field[@name='move_ids_without_package']/tree/field[@name='product_id']" position="after">
                <field name="name"/>
                <!--Campos para el modelo sale.order.line-->
                <field name="sale_line_id" invisible="1"/>
                <field name="sale_price_unit" attrs="{'column_invisible': [('parent.sale_id','=',False)]}"/>
                <field name="sale_discount" attrs="{'column_invisible': [('parent.sale_id','=',False)]}"/>
                <field name="sale_price_subtotal" sum="Subtotal" attrs="{'column_invisible': [('parent.sale_id','=',False)]}"/>
                <!--Campos para el modelo purchase.order.line-->
                <field name="purchase_line_id" invisible="1"/>
                <field name="purchase_price_unit" attrs="{'column_invisible': [('parent.purchase_id','=',False)]}"/>
                <field name="purchase_discount" attrs="{'column_invisible': [('parent.purchase_id','=',False)]}"/>
                <field name="purchase_price_subtotal" sum="Subtotal" attrs="{'column_invisible': [('parent.purchase_id','=',False)]}"/>
            </xpath>

        </field>
    </record>

</odoo>
